dataqa_es/__init__.py
dataqa_es/start_es_server.py
dataqa_es/server/elasticsearch-7.9.2/LICENSE.txt
dataqa_es/server/elasticsearch-7.9.2/NOTICE.txt
dataqa_es/server/elasticsearch-7.9.2/README.asciidoc
dataqa_es/server/elasticsearch-7.9.2/bin/elasticsearch
dataqa_es/server/elasticsearch-7.9.2/bin/elasticsearch-cli
dataqa_es/server/elasticsearch-7.9.2/bin/elasticsearch-env
dataqa_es/server/elasticsearch-7.9.2/bin/elasticsearch-env-from-file
dataqa_es/server/elasticsearch-7.9.2/bin/elasticsearch-keystore
dataqa_es/server/elasticsearch-7.9.2/bin/elasticsearch-node
dataqa_es/server/elasticsearch-7.9.2/bin/elasticsearch-plugin
dataqa_es/server/elasticsearch-7.9.2/bin/elasticsearch-shard
dataqa_es/server/elasticsearch-7.9.2/config/elasticsearch.keystore
dataqa_es/server/elasticsearch-7.9.2/config/elasticsearch.yml
dataqa_es/server/elasticsearch-7.9.2/config/jvm.options
dataqa_es/server/elasticsearch-7.9.2/config/log4j2.properties
dataqa_es/server/elasticsearch-7.9.2/jre-15/release
dataqa_es/server/elasticsearch-7.9.2/jre-15/bin/java
dataqa_es/server/elasticsearch-7.9.2/jre-15/bin/keytool
dataqa_es/server/elasticsearch-7.9.2/jre-15/conf/logging.properties
dataqa_es/server/elasticsearch-7.9.2/jre-15/conf/net.properties
dataqa_es/server/elasticsearch-7.9.2/jre-15/conf/sound.properties
dataqa_es/server/elasticsearch-7.9.2/jre-15/conf/security/java.policy
dataqa_es/server/elasticsearch-7.9.2/jre-15/conf/security/java.security
dataqa_es/server/elasticsearch-7.9.2/jre-15/conf/security/policy/README.txt
dataqa_es/server/elasticsearch-7.9.2/jre-15/conf/security/policy/limited/default_US_export.policy
dataqa_es/server/elasticsearch-7.9.2/jre-15/conf/security/policy/limited/default_local.policy
dataqa_es/server/elasticsearch-7.9.2/jre-15/conf/security/policy/limited/exempt_local.policy
dataqa_es/server/elasticsearch-7.9.2/jre-15/conf/security/policy/unlimited/default_US_export.policy
dataqa_es/server/elasticsearch-7.9.2/jre-15/conf/security/policy/unlimited/default_local.policy
dataqa_es-0.0.3.dist-info/METADATA
dataqa_es-0.0.3.dist-info/WHEEL
dataqa_es-0.0.3.dist-info/entry_points.txt
dataqa_es-0.0.3.dist-info/top_level.txt
dataqa_es-0.0.3.dist-info/RECORD
