Metadata-Version: 2.1
Name: dataqa-es
Version: 0.0.3
Summary: Small ES server for the DataQA platform
Home-page: UNKNOWN
Author: DataQA.AI
Author-email: contact@dataqa.ai
License: UNKNOWN
Platform: UNKNOWN
Requires-Python: >=3.6
